hiccupy.py
hiccupy-1.0.0.dist-info/LICENSE
hiccupy-1.0.0.dist-info/METADATA
hiccupy-1.0.0.dist-info/WHEEL
hiccupy-1.0.0.dist-info/top_level.txt
hiccupy-1.0.0.dist-info/RECORD
