Metadata-Version: 2.1
Name: hiccupy
Version: 1.0.0
Summary: Rendering HTML from hiccup-style lists in python.
Home-page: UNKNOWN
Author: Rebecca Jackson
Author-email: rbca.jackson@gmail.com
License: UNKNOWN
Platform: UNKNOWN
Classifier: Programming Language :: Python :: 3
Classifier: Operating System :: OS Independent
Classifier: License :: OSI Approved :: BSD License
Classifier: Topic :: Text Processing :: Markup :: HTML
License-File: LICENSE
